{
  "id": "ee1f6777-ccab-4771-b8d7-27f01016b953",
  "name": "QuartzMonitor",
  "values": [
    {
      "key": "hostname",
      "value": "localhost",
      "description": "",
      "type": "text",
      "enabled": true
    },
    {
      "key": "port",
      "value": "8889",
      "description": "",
      "type": "text",
      "enabled": true
    },
    {
      "key": "groupName",
      "value": "default",
      "description": "",
      "type": "text",
      "enabled": true
    },
    {
      "key": "jobName",
      "value": "1234567890",
      "description": "",
      "type": "text",
      "enabled": true
    }
  ],
  "_postman_variable_scope": "environment",
  "_postman_exported_at": "2018-11-10T11:46:07.649Z",
  "_postman_exported_using": "Postman/6.0.9"
}